django_pgpy/__init__.py
django_pgpy/apps.py
django_pgpy/auth.py
django_pgpy/defaults.py
django_pgpy/exceptions.py
django_pgpy/forms.py
django_pgpy/hasher.py
django_pgpy/helpers.py
django_pgpy/managers.py
django_pgpy/models.py
django_pgpy/settings.py
django_pgpy/signals.py
django_pgpy/urls.py
django_pgpy/views.py
django_pgpy/migrations/0001_initial.py
django_pgpy/migrations/0002_auto_20200116_1630.py
django_pgpy/migrations/0003_auto_20200129_1723.py
django_pgpy/migrations/0004_auto_20200129_1821.py
django_pgpy/migrations/0005_auto_20200203_1537.py
django_pgpy/migrations/0006_auto_20200203_1555.py
django_pgpy/migrations/0007_auto_20200203_1716.py
django_pgpy/migrations/0008_auto_20250206_2100.py
django_pgpy/migrations/__init__.py
tests/__init__.py
tests/conftest.py
tests/test_auth.py
tests/test_forms.py
tests/test_models.py
tests/test_app/__init__.py
tests/test_app/models.py
tests/test_app/settings.py
tests/test_app/urls.py
tests/test_app/wsgi.py
tests/test_app/migrations/0001_initial.py
tests/test_app/migrations/0002_auto_20200203_1555.py
tests/test_app/migrations/0003_alter_encryptedmessage_text.py
tests/test_app/migrations/__init__.py
django_pgpy-0.2.1.dist-info/LICENSE
django_pgpy-0.2.1.dist-info/METADATA
django_pgpy-0.2.1.dist-info/WHEEL
django_pgpy-0.2.1.dist-info/top_level.txt
django_pgpy-0.2.1.dist-info/zip-safe
django_pgpy-0.2.1.dist-info/RECORD
